{
    "temperature": [
        "Frozen",
        "Variable cold-to-temperate",
        "Cold",
        "Cold",
        "Temperate",
        "Temperate",
        "Temperate",
        "Warm",
        "Warm",
        "Variable temperate-to-warm",
        "Burning"
    ],
    "biosphere": [
        "Biosphere remnants",
        "Microbial life",
        "No native biosphere",
        "No native biosphere",
        "Human-miscible biosphere",
        "Human-miscible biosphere",
        "Human-miscible biosphere",
        "Immiscible biosphere",
        "Immiscible biosphere",
        "Hybrid biosphere",
        "Engineered biosphere"
    ],
    "population": [
        "Failed colony",
        "Outpost",
        "Tens of thousands of inhabitants",
        "Tens of thousands of inhabitants",
        "Hundreds of thousands of inhabitants",
        "Hundreds of thousands of inhabitants",
        "Hundreds of thousands of inhabitants",
        "Millions of inhabitants",
        "Millions of inhabitants",
        "Billions of inhabitants",
        "Alien civilization"
    ],
    "tech_level": [
        "Tech level 0. Stone-age technology.",
        "Tech level 1. Medieval technology.",
        "Tech level 2. Nineteenth-century technology.",
        "Tech level 3. Twentieth-century technology.",
        "Tech level 3. Twentieth-century technology.",
        "Tech level 4. Baseline postech.",
        "Tech level 4. Baseline postech.",
        "Tech level 4. Baseline postech.",
        "Tech level 4. Baseline postech.",
        "Tech level 4 with specialties or some surviving pretech.",
        "Tech level 5. Pretech, pre-Silence technology."
    ],
    "tags": [
        "Abandoned Colony",
        "Alien Ruins",
        "Altered Humanity",
        "Area 51",
        "Badlands World",
        "Bubble Cities",
        "Civil War",
        "Cold War",
        "Colonized Population",
        "Desert World",
        "Eugenic Cult",
        "Exchange Consulate",
        "Feral World",
        "Flying Cities",
        "Forbidden Tech",
        "Freak Geology",
        "Freak Weather",
        "Friendly Foe",
        "Gold Rush",
        "Hatred",
        "Heavy Industry",
        "Heavy Mining",
        "Hostile Biosphere",
        "Hostile Space",
        "Local Specialty",
        "Local Tech",
        "Major Spaceyard",
        "Minimal Contact",
        "Misandry/Misoginy",
        "Oceanic World",
        "Out of Contact",
        "Outpost World",
        "Perimeter Agency",
        "Pilgrimage Site",
        "Police State",
        "Preceptor Archive",
        "Pretech Cultists",
        "Primitive Aliens",
        "Psionics Fear",
        "Psionics Worship",
        "Psionics Academy",
        "Quarantined World",
        "Radioactive World",
        "Regional Hegemon",
        "Restrictive Laws",
        "Rigid Culture",
        "Seagoing Cities",
        "Sealed Menace",
        "Sectarians",
        "Seismic Activity",
        "Secret Masters",
        "Theocracy",
        "Tomb World",
        "Trade Hub",
        "Tyranny",
        "Unbraked AI",
        "Warlords",
        "Xenophiles",
        "Xenophobes",
        "Zombies"
    ],
    "atmosphere": [
        "Corrosive",
        "Inert gas",
        "Airless or thin atmosphere",
        "Breathable mix",
        "Breathable mix",
        "Breathable mix",
        "Breathable mix",
        "Breathable mix",
        "Thick atmosphere, breathable with a pressure mask",
        "Invasive, toxic atmosphere",
        "Corrosive and invasive atmosphere"
    ]
}
